ARMBR/BCI2000GUI.py
ARMBR/__init__.py
ARMBR/__main__.py
ARMBR/armbr.py
ARMBR/mne_test_armbr.py
armbr-2.0.12.dist-info/licenses/LICENSE.txt
armbr-2.0.12.dist-info/METADATA
armbr-2.0.12.dist-info/WHEEL
armbr-2.0.12.dist-info/top_level.txt
armbr-2.0.12.dist-info/RECORD
