Metadata-Version: 2.4
Name: ARMBR
Version: 2.0.12
Summary: Python implementation of the ARMBR blink removal method
Home-page: https://github.com/S-Shah-Lab/ARMBR.git
Author: Ludvik Alkhoury
Author-email: Ludvik.Alkhoury@gmail.com
License: GPL-3.0-only
Classifier: License :: OSI Approved :: GNU General Public License v3 (GPLv3)
Classifier: Programming Language :: Python :: 3
Classifier: Operating System :: OS Independent
License-File: LICENSE.txt
Requires-Dist: scipy
Requires-Dist: numpy
Dynamic: author
Dynamic: author-email
Dynamic: classifier
Dynamic: description
Dynamic: description-content-type
Dynamic: home-page
Dynamic: license
Dynamic: license-file
Dynamic: requires-dist
Dynamic: summary
